<?xml version='1.0' encoding='UTF-8'?>
<list xmlns:xsi="http://www.w3.org/2001/XMLSchema-instance" xsi:noNamespaceSchemaLocation="../xsd/buylist.xsd">
  <npcs>
    <npc>31968</npc>
  </npcs>
  <item id="1902" />
  <item id="1903" />
  <item id="1904" />
  <item id="1905" />
  <item id="1906" />
  <item id="1907" />
  <item id="1908" />
  <item id="1909" />
  <item id="1910" />
  <item id="1911" />
  <item id="1912" />
  <item id="1913" />
  <item id="1914" />
  <item id="1915" />
  <item id="1916" />
  <item id="1917" />
  <item id="1918" />
  <item id="1919" />
  <item id="1920" />
  <item id="1921" />
  <item id="1922" />
  <item id="1923" />
  <item id="1924" />
  <item id="1925" />
  <item id="1926" />
  <item id="1927" />
  <item id="1928" />
  <item id="1929" />
  <item id="1930" />
  <item id="1931" />
  <item id="1932" />
  <item id="1933" />
  <item id="1934" />
  <item id="1935" />
  <item id="1936" />
  <item id="1937" />
  <item id="1938" />
  <item id="1939" />
  <item id="1940" />
  <item id="1941" />
  <item id="1942" />
  <item id="1943" />
  <item id="1944" />
  <item id="1945" />
  <item id="1946" />
  <item id="1947" />
  <item id="1948" />
  <item id="1949" />
  <item id="1950" />
  <item id="1951" />
</list>